simplelimiter/__init__.py
simplelimiter-0.1.4.dist-info/LICENSE
simplelimiter-0.1.4.dist-info/METADATA
simplelimiter-0.1.4.dist-info/WHEEL
simplelimiter-0.1.4.dist-info/RECORD
