Metadata-Version: 2.1
Name: simplelimiter
Version: 0.1.4
Summary: Simple FastAPI rate limiter
License: MIT
Author: Fabrizio Liotta
Requires-Python: >=3.10,<4.0
Classifier: License :: OSI Approved :: MIT License
Classifier: Programming Language :: Python :: 3
Classifier: Programming Language :: Python :: 3.10
Classifier: Programming Language :: Python :: 3.11
Requires-Dist: fastapi (>=0.103.1,<0.104.0)
Requires-Dist: redis (>=5.0.0,<6.0.0)
